{"frames": {

"island_bg-afternoon.png":
{
	"frame": {"x":0,"y":0,"w":1920,"h":1080},
	"rotated": false,
	"trimmed": false,
	"spriteSourceSize": {"x":0,"y":0,"w":1920,"h":1080},
	"sourceSize": {"w":1920,"h":1080}
}},
"meta": {
	"app": "https://www.codeandweb.com/texturepacker",
	"version": "1.0",
	"image": "afternoonBG.png",
	"format": "RGBA8888",
	"size": {"w":1920,"h":1080},
	"scale": "1",
	"smartupdate": "$TexturePacker:SmartUpdate:d70184e502c8a4dd67066d15be32961d:121141eaae3847e25c2ade24ff918f12:eb90b808e36771242aa8f8875d5df47c$"
}
}
